<?xml version="1.0" encoding="UTF-8"?>
<root>
<sta_battlePalaceMonsterSkill id="1" pokeId="31" skill="58|53|414|85" weight="100" features="79|38" fruit="118|125" prop="113|115|935"/>
<sta_battlePalaceMonsterSkill id="2" pokeId="31" skill="188|414|53|85" weight="100" features="79|38" fruit="118|125" prop="113|115|935"/>
<sta_battlePalaceMonsterSkill id="3" pokeId="34" skill="89|92|390|8" weight="100" features="79|38" fruit="118|125" prop="113|115|935"/>
<sta_battlePalaceMonsterSkill id="4" pokeId="34" skill="57|89|414|85" weight="100" features="79|38" fruit="118|125" prop="113|115|935"/>
<sta_battlePalaceMonsterSkill id="5" pokeId="38" skill="92|412|261|326" weight="100" features="18|70" fruit="118|125" prop="106"/>
<sta_battlePalaceMonsterSkill id="6" pokeId="38" skill="261|53|109|326" weight="100" features="18|70" fruit="118|125" prop="106"/>
<sta_battlePalaceMonsterSkill id="7" pokeId="59" skill="528|394|245|370" weight="100" features="18|22|154" fruit="118|125" prop="106|739"/>
<sta_battlePalaceMonsterSkill id="8" pokeId="59" skill="528|394|261|370" weight="100" features="18|22|154" fruit="118|125" prop="106|739"/>
<sta_battlePalaceMonsterSkill id="9" pokeId="68" skill="8|7|370|339" weight="100" features="62|80|99" fruit="118|125" prop="946|732|935"/>
<sta_battlePalaceMonsterSkill id="10" pokeId="68" skill="238|8|34|157" weight="100" features="62|80|99" fruit="118|125" prop="946|732|935"/>
<sta_battlePalaceMonsterSkill id="11" pokeId="91" skill="191|58|390|57" weight="100" features="75|142" fruit="118|125" prop="1594"/>
<sta_battlePalaceMonsterSkill id="12" pokeId="91" skill="333|350|504|534" weight="100" features="75|142" fruit="118|125" prop="1594"/>
<sta_battlePalaceMonsterSkill id="13" pokeId="103" skill="94|414|73|109" weight="100" features="34" fruit="118|125" prop="110|745|737"/>
<sta_battlePalaceMonsterSkill id="14" pokeId="103" skill="29|92|94|202" weight="100" features="34" fruit="118|125" prop="110|745|737"/>
<sta_battlePalaceMonsterSkill id="15" pokeId="121" skill="85|58|57|92" weight="100" features="67|148" fruit="118|125" prop="935|109|739"/>
<sta_battlePalaceMonsterSkill id="16" pokeId="121" skill="94|85|58|57" weight="100" features="67|148" fruit="118|125" prop="935|109|739"/>
<sta_battlePalaceMonsterSkill id="17" pokeId="124" skill="58|94|247|324" weight="100" features="87|12" fruit="118|125" prop="935|110|5241"/>
<sta_battlePalaceMonsterSkill id="18" pokeId="124" skill="3|37|115|113" weight="100" features="87|12" fruit="118|125" prop="935|110|5241"/>
<sta_battlePalaceMonsterSkill id="19" pokeId="131" skill="156|214|32|329" weight="100" features="75|93|11|186" fruit="118|125" prop="745|732|109"/>
<sta_battlePalaceMonsterSkill id="20" pokeId="131" skill="92|182|57|58" weight="100" features="75|93|11|186" fruit="118|125" prop="745|732|109"/>
<sta_battlePalaceMonsterSkill id="21" pokeId="134" skill="92|273|503|182" weight="100" features="93|11" fruit="118|125" prop="1594|745|109"/>
<sta_battlePalaceMonsterSkill id="22" pokeId="134" skill="273|151|503|226" weight="100" features="93|11" fruit="118|125" prop="1594|745|109"/>
<sta_battlePalaceMonsterSkill id="23" pokeId="135" skill="480|85|182|521" weight="100" features="10|95|211" fruit="118|125" prop="116|734"/>
<sta_battlePalaceMonsterSkill id="24" pokeId="135" skill="92|521|182|273" weight="100" features="10|95|211" fruit="118|125" prop="116|734"/>
<sta_battlePalaceMonsterSkill id="25" pokeId="136" skill="424|416|261|241" weight="100" features="18|62" fruit="118|125" prop="106|734"/>
<sta_battlePalaceMonsterSkill id="26" pokeId="136" skill="53|92|273|164" weight="100" features="18|62" fruit="118|125" prop="106|734"/>
<sta_battlePalaceMonsterSkill id="27" pokeId="139" skill="390|446|57|58" weight="100" features="75|33" fruit="118|125" prop="1594|737"/>
<sta_battlePalaceMonsterSkill id="28" pokeId="139" skill="57|58|479|240" weight="100" features="75|33" fruit="118|125" prop="1594|737"/>
<sta_battlePalaceMonsterSkill id="29" pokeId="141" skill="127|14|444|276" weight="100" features="33|4" fruit="118|125" prop="1594|737"/>
<sta_battlePalaceMonsterSkill id="30" pokeId="141" skill="14|127|444|404" weight="100" features="33|4" fruit="118|125" prop="1594|737"/>
<sta_battlePalaceMonsterSkill id="31" pokeId="143" skill="156|174|242|89" weight="100" features="47|17|96" fruit="118|125" prop="108|5242|5241|745"/>
<sta_battlePalaceMonsterSkill id="32" pokeId="143" skill="89|156|174|34" weight="100" features="47|17|96" fruit="118|125" prop="108|5242|5241|745"/>
<sta_battlePalaceMonsterSkill id="33" pokeId="144" skill="58|314|466|477" weight="100" features="46|81" fruit="118|125" prop="935|112"/>
<sta_battlePalaceMonsterSkill id="34" pokeId="144" skill="164|92|355|58" weight="100" features="46|81" fruit="118|125" prop="935|112"/>
<sta_battlePalaceMonsterSkill id="35" pokeId="146" skill="53|403|246|478" weight="100" features="49|46" fruit="118|125" prop="935|106"/>
<sta_battlePalaceMonsterSkill id="36" pokeId="146" skill="355|164|92|53" weight="100" features="49|46" fruit="118|125" prop="935|106"/>
<sta_battlePalaceMonsterSkill id="37" pokeId="150" skill="94|396|58|85" weight="100" features="46|127" fruit="118|125" prop="935|950"/>
<sta_battlePalaceMonsterSkill id="38" pokeId="150" skill="94|396|53|247" weight="100" features="46|127" fruit="118|125" prop="935|950"/>
<sta_battlePalaceMonsterSkill id="39" pokeId="151" skill="94|396|247|347" weight="100" features="28" fruit="118|125" prop="935|110"/>
<sta_battlePalaceMonsterSkill id="40" pokeId="151" skill="14|7|280|89" weight="100" features="28" fruit="118|125" prop="935|110"/>
<sta_battlePalaceMonsterSkill id="41" pokeId="154" skill="73|92|412|164" weight="100" features="65|102" fruit="118|125" prop="2766|1594"/>
<sta_battlePalaceMonsterSkill id="42" pokeId="154" skill="14|402|89|200" weight="100" features="65|102" fruit="118|125" prop="2766|1594"/>
<sta_battlePalaceMonsterSkill id="43" pokeId="157" skill="284|53|411|471" weight="100" features="18|66" fruit="118|125" prop="2767|106"/>
<sta_battlePalaceMonsterSkill id="44" pokeId="157" skill="164|104|92|53" weight="100" features="18|66" fruit="118|125" prop="2767|106"/>
<sta_battlePalaceMonsterSkill id="45" pokeId="160" skill="89|127|157|242" weight="100" features="55|67|125" fruit="118|125" prop="2768|946"/>
<sta_battlePalaceMonsterSkill id="46" pokeId="160" skill="349|127|89|157" weight="100" features="55|67|125" fruit="118|125" prop="2768|946"/>
<sta_battlePalaceMonsterSkill id="47" pokeId="181" skill="87|480|86|113" weight="100" features="10|78" fruit="118|125" prop="116"/>
<sta_battlePalaceMonsterSkill id="48" pokeId="181" skill="85|480|86|268" weight="100" features="10|78" fruit="118|125" prop="116"/>
<sta_battlePalaceMonsterSkill id="49" pokeId="186" skill="92|503|479|182" weight="100" features="2|11" fruit="118|125" prop="109"/>
<sta_battlePalaceMonsterSkill id="50" pokeId="186" skill="503|240|182|92" weight="100" features="2|11" fruit="118|125" prop="109"/>
<sta_battlePalaceMonsterSkill id="51" pokeId="196" skill="94|605|164|116" weight="100" features="28" fruit="118|125" prop="110|935"/>
<sta_battlePalaceMonsterSkill id="52" pokeId="196" skill="94|605|247|116" weight="100" features="28" fruit="118|125" prop="110|935"/>
<sta_battlePalaceMonsterSkill id="53" pokeId="197" skill="492|182|273|104" weight="100" features="39|28" fruit="118|125" prop="1594|745"/>
<sta_battlePalaceMonsterSkill id="54" pokeId="197" skill="92|174|236|371" weight="100" features="39|28" fruit="118|125" prop="1594|745"/>
<sta_battlePalaceMonsterSkill id="55" pokeId="199" skill="57|92|156|214" weight="100" features="144|20|12" fruit="118|125" prop="1594|745"/>
<sta_battlePalaceMonsterSkill id="56" pokeId="199" skill="94|57|58|126" weight="100" features="144|20|12" fruit="118|125" prop="1594|745"/>
<sta_battlePalaceMonsterSkill id="57" pokeId="208" skill="89|446|92|46" weight="100" features="69|5" fruit="118|125" prop="1594|113|745"/>
<sta_battlePalaceMonsterSkill id="58" pokeId="208" skill="174|89|422|444" weight="100" features="69|5" fruit="118|125" prop="1594|113|745"/>
<sta_battlePalaceMonsterSkill id="59" pokeId="212" skill="14|404|418|276" weight="100" features="101|80" fruit="118|125" prop="946|739"/>
<sta_battlePalaceMonsterSkill id="60" pokeId="212" skill="355|164|92|29" weight="100" features="101|80" fruit="118|125" prop="946|739"/>
<sta_battlePalaceMonsterSkill id="61" pokeId="214" skill="92|164|224|179" weight="100" features="62|68" fruit="118|125" prop="732|946|739"/>
<sta_battlePalaceMonsterSkill id="62" pokeId="214" skill="89|164|224|179" weight="100" features="62|68" fruit="118|125" prop="732|946|739"/>
<sta_battlePalaceMonsterSkill id="63" pokeId="229" skill="188|53|399|417" weight="100" features="18|127|48" fruit="118|125" prop="106|935"/>
<sta_battlePalaceMonsterSkill id="64" pokeId="229" skill="261|194|294|399" weight="100" features="18|127|48" fruit="118|125" prop="106|935"/>
<sta_battlePalaceMonsterSkill id="65" pokeId="230" skill="57|58|406|200" weight="100" features="97|33" fruit="118|125" prop="109|935|107"/>
<sta_battlePalaceMonsterSkill id="66" pokeId="230" skill="57|58|116|434" weight="100" features="97|33" fruit="118|125" prop="109|935|107"/>
<sta_battlePalaceMonsterSkill id="67" pokeId="233" skill="92|105|58|85" weight="100" features="88" fruit="118|125" prop="935|955"/>
<sta_battlePalaceMonsterSkill id="68" pokeId="233" skill="58|161|105|492" weight="100" features="88" fruit="118|125" prop="935|955"/>
<sta_battlePalaceMonsterSkill id="69" pokeId="242" skill="68|135|92|69" weight="100" features="32|12" fruit="118|125" prop="745|1594"/>
<sta_battlePalaceMonsterSkill id="70" pokeId="242" skill="107|92|135|247" weight="100" features="32|12" fruit="118|125" prop="745|1594"/>
<sta_battlePalaceMonsterSkill id="71" pokeId="243" skill="164|347|85|326" weight="100" features="10|46|211" fruit="118|125" prop="116|739|935"/>
<sta_battlePalaceMonsterSkill id="72" pokeId="243" skill="104|164|85|326" weight="100" features="10|46|211" fruit="118|125" prop="116|739|935"/>
<sta_battlePalaceMonsterSkill id="73" pokeId="244" skill="347|164|53|326" weight="100" features="46|18" fruit="118|125" prop="106|739|935"/>
<sta_battlePalaceMonsterSkill id="74" pokeId="244" skill="247|478|53|326" weight="100" features="46|18" fruit="118|125" prop="106|739|935"/>
<sta_battlePalaceMonsterSkill id="75" pokeId="245" skill="156|347|57|326" weight="100" features="46|114|11" fruit="118|125" prop="109|745|1594"/>
<sta_battlePalaceMonsterSkill id="76" pokeId="245" skill="57|58|326|247" weight="100" features="46|114|11" fruit="118|125" prop="109|745|1594"/>
<sta_battlePalaceMonsterSkill id="77" pokeId="249" skill="347|105|177|94" weight="100" features="46|136" fruit="118|125" prop="2868|955|935"/>
<sta_battlePalaceMonsterSkill id="78" pokeId="249" skill="92|105|164|177" weight="100" features="46|136" fruit="118|125" prop="2868|955|935"/>
<sta_battlePalaceMonsterSkill id="79" pokeId="250" skill="53|414|85|247" weight="100" features="46|144" fruit="118|125" prop="1567|106|739"/>
<sta_battlePalaceMonsterSkill id="80" pokeId="250" skill="347|105|53|85" weight="100" features="46|144" fruit="118|125" prop="1567|106|739"/>
<sta_battlePalaceMonsterSkill id="81" pokeId="289" skill="175|116|164|179" weight="100" features="" fruit="118|125" prop="745|5242|5241|946"/>
<sta_battlePalaceMonsterSkill id="82" pokeId="289" skill="34|303|7|280" weight="100" features="" fruit="118|125" prop="745|5242|5241|946"/>
<sta_battlePalaceMonsterSkill id="83" pokeId="330" skill="89|200|7|369" weight="100" features="26" fruit="118|125" prop="113|946|5242|5241"/>
<sta_battlePalaceMonsterSkill id="84" pokeId="330" skill="202|434|414|53" weight="100" features="26" fruit="118|125" prop="113|946|5242|5241"/>
<sta_battlePalaceMonsterSkill id="85" pokeId="350" skill="57|58|406|105" weight="100" features="63" fruit="118|125" prop="1594|109"/>
<sta_battlePalaceMonsterSkill id="86" pokeId="350" skill="156|92|57|243" weight="100" features="63" fruit="118|125" prop="1594|109"/>
<sta_battlePalaceMonsterSkill id="87" pokeId="373" skill="200|89|444|424" weight="100" features="22" fruit="118|125" prop="5573|107"/>
<sta_battlePalaceMonsterSkill id="88" pokeId="373" skill="337|349|89|444" weight="100" features="22" fruit="118|125" prop="5573|107"/>
<sta_battlePalaceMonsterSkill id="89" pokeId="377" skill="444|89|276|7" weight="100" features="5|29" fruit="118|125" prop="1594|745"/>
<sta_battlePalaceMonsterSkill id="90" pokeId="377" skill="174|444|89|359" weight="100" features="5|29" fruit="118|125" prop="1594|745"/>
<sta_battlePalaceMonsterSkill id="91" pokeId="378" skill="85|58|246|411" weight="100" features="5|29" fruit="118|125" prop="1594|745"/>
<sta_battlePalaceMonsterSkill id="92" pokeId="378" skill="92|164|258|477" weight="100" features="5|29" fruit="118|125" prop="1594|745"/>
<sta_battlePalaceMonsterSkill id="93" pokeId="379" skill="174|359|89|157" weight="100" features="5|29" fruit="118|125" prop="1594|745"/>
<sta_battlePalaceMonsterSkill id="94" pokeId="379" skill="446|92|334|89" weight="100" features="5|29" fruit="118|125" prop="1594|745"/>
<sta_battlePalaceMonsterSkill id="95" pokeId="380" skill="406|58|85|94" weight="100" features="26" fruit="118|125" prop="852|935|110"/>
<sta_battlePalaceMonsterSkill id="96" pokeId="380" skill="347|406|58|105" weight="100" features="26" fruit="118|125" prop="852|935|110"/>
<sta_battlePalaceMonsterSkill id="97" pokeId="381" skill="406|105|94|247" weight="100" features="26" fruit="118|125" prop="852|935|110"/>
<sta_battlePalaceMonsterSkill id="98" pokeId="381" skill="406|85|247|105" weight="100" features="26" fruit="118|125" prop="852|935|110"/>
<sta_battlePalaceMonsterSkill id="99" pokeId="382" skill="57|58|87|246" weight="100" features="2" fruit="118|125" prop="854|955"/>
<sta_battlePalaceMonsterSkill id="100" pokeId="382" skill="87|57|58|347" weight="100" features="2" fruit="118|125" prop="854|955"/>
<sta_battlePalaceMonsterSkill id="101" pokeId="383" skill="89|14|510|444" weight="100" features="70" fruit="118|125" prop="855|946"/>
<sta_battlePalaceMonsterSkill id="102" pokeId="383" skill="7|619|156|164" weight="100" features="70" fruit="118|125" prop="855|946"/>
<sta_battlePalaceMonsterSkill id="103" pokeId="384" skill="14|164|200|620" weight="100" features="46|127" fruit="118|125" prop="951|2867|107"/>
<sta_battlePalaceMonsterSkill id="104" pokeId="384" skill="245|337|89|242" weight="100" features="46|127" fruit="118|125" prop="951|2867|107"/>
<sta_battlePalaceMonsterSkill id="105" pokeId="385" skill="273|92|94|113" weight="100" features="32" fruit="118|125" prop="745|110"/>
<sta_battlePalaceMonsterSkill id="106" pokeId="385" skill="361|247|87|93" weight="100" features="32" fruit="118|125" prop="745|110"/>
<sta_battlePalaceMonsterSkill id="107" pokeId="386" skill="58|276|85|354" weight="100" features="46|26" fruit="118|125" prop="739|955"/>
<sta_battlePalaceMonsterSkill id="108" pokeId="386" skill="63|94|101|58" weight="100" features="46|26" fruit="118|125" prop="739|955"/>
<sta_battlePalaceMonsterSkill id="109" pokeId="389" skill="242|89|331|157" weight="100" features="65|75" fruit="118|125" prop="113|732"/>
<sta_battlePalaceMonsterSkill id="110" pokeId="389" skill="89|92|73|164" weight="100" features="65|75" fruit="118|125" prop="113|732"/>
<sta_battlePalaceMonsterSkill id="111" pokeId="392" skill="370|7|9|89" weight="100" features="66|89" fruit="118|125" prop="935|739"/>
<sta_battlePalaceMonsterSkill id="112" pokeId="392" skill="347|53|253|411" weight="100" features="66|89" fruit="118|125" prop="935|739"/>
<sta_battlePalaceMonsterSkill id="113" pokeId="395" skill="57|430|58|97" weight="100" features="67|114" fruit="118|125" prop="109|1594"/>
<sta_battlePalaceMonsterSkill id="114" pokeId="395" skill="92|57|156|446" weight="100" features="67|114" fruit="118|125" prop="109|1594"/>
<sta_battlePalaceMonsterSkill id="115" pokeId="411" skill="68|92|156|157" weight="100" features="5|43" fruit="118|125" prop="1594|737"/>
<sta_battlePalaceMonsterSkill id="116" pokeId="411" skill="368|269|419|444" weight="100" features="5|43" fruit="118|125" prop="1594|737"/>
<sta_battlePalaceMonsterSkill id="117" pokeId="435" skill="400|269|432|53" weight="100" features="51|106" fruit="118|125" prop="737"/>
<sta_battlePalaceMonsterSkill id="118" pokeId="435" skill="389|53|432|398" weight="100" features="51|106" fruit="118|125" prop="737"/>
<sta_battlePalaceMonsterSkill id="119" pokeId="437" skill="115|153|430|433" weight="100" features="26" fruit="118|125" prop="1594|745"/>
<sta_battlePalaceMonsterSkill id="120" pokeId="437" skill="95|93|347|247" weight="100" features="26" fruit="118|125" prop="1594|745"/>
<sta_battlePalaceMonsterSkill id="121" pokeId="442" skill="347|247|156|468" weight="100" features="46" fruit="118|125" prop="745|1594"/>
<sta_battlePalaceMonsterSkill id="122" pokeId="442" skill="466|389|261|164" weight="100" features="46" fruit="118|125" prop="745|1594"/>
<sta_battlePalaceMonsterSkill id="123" pokeId="445" skill="14|89|337|157" weight="100" features="8|61|24" fruit="118|125" prop="739|113|107"/>
<sta_battlePalaceMonsterSkill id="124" pokeId="445" skill="14|89|242|424" weight="100" features="8|61|24" fruit="118|125" prop="739|113|107"/>
<sta_battlePalaceMonsterSkill id="125" pokeId="450" skill="89|46|303|423" weight="100" features="45" fruit="118|125" prop="1594|113|745"/>
<sta_battlePalaceMonsterSkill id="126" pokeId="450" skill="446|46|182|89" weight="100" features="45" fruit="118|125" prop="1594|113|745"/>
<sta_battlePalaceMonsterSkill id="127" pokeId="452" skill="400|424|89|269" weight="100" features="97|4" fruit="118|125" prop="5242|5241"/>
<sta_battlePalaceMonsterSkill id="128" pokeId="452" skill="390|46|423|440" weight="100" features="97|4" fruit="118|125" prop="5242|5241"/>
<sta_battlePalaceMonsterSkill id="129" pokeId="460" skill="59|182|202|73" weight="100" features="117|43" fruit="118|125" prop="112|732"/>
<sta_battlePalaceMonsterSkill id="130" pokeId="460" skill="8|157|402|14" weight="100" features="117|43" fruit="118|125" prop="112|732"/>
<sta_battlePalaceMonsterSkill id="131" pokeId="461" skill="400|8|280|14" weight="100" features="46" fruit="118|125" prop="112|946|5242|5241"/>
<sta_battlePalaceMonsterSkill id="132" pokeId="461" skill="421|490|492|8" weight="100" features="46" fruit="118|125" prop="112|946|5242|5241"/>
<sta_battlePalaceMonsterSkill id="133" pokeId="462" skill="85|182|430|521" weight="100" features="5|148|42" fruit="118|125" prop="955|737"/>
<sta_battlePalaceMonsterSkill id="134" pokeId="462" skill="85|243|471|521" weight="100" features="5|148|42" fruit="118|125" prop="955|737"/>
<sta_battlePalaceMonsterSkill id="135" pokeId="466" skill="89|8|9|7" weight="100" features="9|78" fruit="118|125" prop="955|116"/>
<sta_battlePalaceMonsterSkill id="136" pokeId="466" skill="164|521|612|8" weight="100" features="9|78" fruit="118|125" prop="955|116"/>
<sta_battlePalaceMonsterSkill id="137" pokeId="467" skill="85|94|126|253" weight="100" features="49" fruit="118|125" prop="955|106"/>
<sta_battlePalaceMonsterSkill id="138" pokeId="467" skill="269|53|280|63" weight="100" features="49" fruit="118|125" prop="955|106"/>
<sta_battlePalaceMonsterSkill id="139" pokeId="468" skill="396|403|63|417" weight="100" features="105|32|191" fruit="118|125" prop="955|739"/>
<sta_battlePalaceMonsterSkill id="140" pokeId="468" skill="94|156|173|605" weight="100" features="105|32|191" fruit="118|125" prop="955|739"/>
<sta_battlePalaceMonsterSkill id="141" pokeId="470" skill="348|241|14|404" weight="100" features="34" fruit="118|125" prop="739|946"/>
<sta_battlePalaceMonsterSkill id="142" pokeId="470" skill="226|14|320|402" weight="100" features="34" fruit="118|125" prop="739|946"/>
<sta_battlePalaceMonsterSkill id="143" pokeId="471" skill="258|59|247|304" weight="100" features="81|115|186" fruit="118|125" prop="739|112"/>
<sta_battlePalaceMonsterSkill id="144" pokeId="471" skill="313|58|63|352" weight="100" features="81|115|186" fruit="118|125" prop="739|112"/>
<sta_battlePalaceMonsterSkill id="145" pokeId="472" skill="14|424|89|157" weight="100" features="52|8|90" fruit="118|125" prop="113|5242|5241"/>
<sta_battlePalaceMonsterSkill id="146" pokeId="472" skill="92|91|182|201" weight="100" features="52|8|90" fruit="118|125" prop="113|5242|5241"/>
<sta_battlePalaceMonsterSkill id="147" pokeId="474" skill="433|85|63|324" weight="100" features="91|148|88" fruit="118|125" prop="955|935"/>
<sta_battlePalaceMonsterSkill id="148" pokeId="474" skill="417|161|58|94" weight="100" features="91|148|88" fruit="118|125" prop="955|935"/>
<sta_battlePalaceMonsterSkill id="149" pokeId="477" skill="425|371|156|7" weight="100" features="46" fruit="118|125" prop="946|732"/>
<sta_battlePalaceMonsterSkill id="150" pokeId="477" skill="347|58|156|247" weight="100" features="46" fruit="118|125" prop="946|732"/>
<sta_battlePalaceMonsterSkill id="151" pokeId="478" skill="109|174|247|577" weight="100" features="81|130" fruit="118|125" prop="955|935"/>
<sta_battlePalaceMonsterSkill id="152" pokeId="478" skill="58|85|269|506" weight="100" features="81|130" fruit="118|125" prop="955|935"/>
<sta_battlePalaceMonsterSkill id="153" pokeId="479" skill="164|399|85|86" weight="100" features="26" fruit="118|125" prop="955"/>
<sta_battlePalaceMonsterSkill id="154" pokeId="479" skill="182|261|521|247" weight="100" features="26" fruit="118|125" prop="955"/>
<sta_battlePalaceMonsterSkill id="155" pokeId="480" skill="156|85|94|347" weight="100" features="26" fruit="118|125" prop="745"/>
<sta_battlePalaceMonsterSkill id="156" pokeId="480" skill="92|156|446|94" weight="100" features="26" fruit="118|125" prop="745"/>
<sta_battlePalaceMonsterSkill id="157" pokeId="481" skill="58|85|247|347" weight="100" features="26" fruit="118|125" prop="955"/>
<sta_battlePalaceMonsterSkill id="158" pokeId="481" skill="58|9|7|605" weight="100" features="26" fruit="118|125" prop="955"/>
<sta_battlePalaceMonsterSkill id="159" pokeId="482" skill="347|53|85|247" weight="100" features="26" fruit="118|125" prop="955"/>
<sta_battlePalaceMonsterSkill id="160" pokeId="482" skill="369|7|9|153" weight="100" features="26" fruit="118|125" prop="955"/>
<sta_battlePalaceMonsterSkill id="161" pokeId="483" skill="337|89|430|156" weight="100" features="46" fruit="118|125" prop="943|955"/>
<sta_battlePalaceMonsterSkill id="162" pokeId="483" skill="459|53|46|446" weight="100" features="46" fruit="118|125" prop="943|955"/>
<sta_battlePalaceMonsterSkill id="163" pokeId="484" skill="460|414|57|164" weight="100" features="46" fruit="118|125" prop="932|955"/>
<sta_battlePalaceMonsterSkill id="164" pokeId="484" skill="396|58|156|214" weight="100" features="46" fruit="118|125" prop="932|955"/>
<sta_battlePalaceMonsterSkill id="165" pokeId="485" skill="76|414|126|241" weight="100" features="18|49" fruit="118|125" prop="955|732"/>
<sta_battlePalaceMonsterSkill id="166" pokeId="485" skill="89|153|317|53" weight="100" features="18|49" fruit="118|125" prop="955|732"/>
<sta_battlePalaceMonsterSkill id="167" pokeId="486" skill="7|8|9|409" weight="100" features="5" fruit="118|125" prop="946|745"/>
<sta_battlePalaceMonsterSkill id="168" pokeId="486" skill="276|89|356|157" weight="100" features="5" fruit="118|125" prop="946|745"/>
<sta_battlePalaceMonsterSkill id="169" pokeId="487" skill="246|156|396|247" weight="100" features="46" fruit="118|125" prop="931|107|745"/>
<sta_battlePalaceMonsterSkill id="170" pokeId="487" skill="156|92|406|104" weight="100" features="46" fruit="118|125" prop="931|107|745"/>
<sta_battlePalaceMonsterSkill id="171" pokeId="488" skill="585|94|433|461" weight="100" features="26" fruit="118|125" prop="745|1594"/>
<sta_battlePalaceMonsterSkill id="172" pokeId="488" skill="324|104|92|156" weight="100" features="26" fruit="118|125" prop="745|1594"/>
<sta_battlePalaceMonsterSkill id="173" pokeId="489" skill="240|156|92|250" weight="100" features="93" fruit="118|125" prop="109"/>
<sta_battlePalaceMonsterSkill id="174" pokeId="489" skill="58|57|369|182" weight="100" features="93" fruit="118|125" prop="109"/>
<sta_battlePalaceMonsterSkill id="175" pokeId="490" skill="294|58|57|247" weight="100" features="93" fruit="118|125" prop="109"/>
<sta_battlePalaceMonsterSkill id="176" pokeId="490" skill="156|240|250|92" weight="100" features="93" fruit="118|125" prop="109"/>
<sta_battlePalaceMonsterSkill id="177" pokeId="491" skill="171|464|138|399" weight="100" features="123" fruit="118|125" prop="955|950|935"/>
<sta_battlePalaceMonsterSkill id="178" pokeId="491" skill="464|417|58|85" weight="100" features="123" fruit="118|125" prop="955|950|935"/>
<sta_battlePalaceMonsterSkill id="179" pokeId="492" skill="235|465|241|605" weight="100" features="30" fruit="118|125" prop="955"/>
<sta_battlePalaceMonsterSkill id="180" pokeId="492" skill="235|414|92|312" weight="100" features="30" fruit="118|125" prop="955"/>
<sta_battlePalaceMonsterSkill id="181" pokeId="500" skill="523|7|276|528" weight="100" features="66" fruit="118|125" prop="732|946"/>
<sta_battlePalaceMonsterSkill id="182" pokeId="500" skill="503|53|9|428" weight="100" features="66" fruit="118|125" prop="732|946"/>
<sta_battlePalaceMonsterSkill id="183" pokeId="503" skill="534|14|224|400" weight="100" features="67" fruit="118|125" prop="109|955"/>
<sta_battlePalaceMonsterSkill id="184" pokeId="503" skill="57|58|403|63" weight="100" features="67" fruit="118|125" prop="109|955"/>
<sta_battlePalaceMonsterSkill id="185" pokeId="530" skill="89|157|442|398" weight="100" features="146|159" fruit="118|125" prop="113|1594|946"/>
<sta_battlePalaceMonsterSkill id="186" pokeId="530" skill="89|157|201|442" weight="100" features="146|159" fruit="118|125" prop="113|1594|946"/>
<sta_battlePalaceMonsterSkill id="187" pokeId="534" skill="89|157|359|371" weight="100" features="62|125|89" fruit="118|125" prop="946|732|745"/>
<sta_battlePalaceMonsterSkill id="188" pokeId="534" skill="409|7|8|9" weight="100" features="62|125|89" fruit="118|125" prop="946|732|745"/>
<sta_battlePalaceMonsterSkill id="189" pokeId="538" skill="7|8|9|67" weight="100" features="62|39|104" fruit="118|125" prop="946|739|5242"/>
<sta_battlePalaceMonsterSkill id="190" pokeId="538" skill="89|157|398|10480" weight="100" features="62|39|104" fruit="118|125" prop="946|739|5242"/>
<sta_battlePalaceMonsterSkill id="191" pokeId="539" skill="7|8|9|67" weight="100" features="5|39|104" fruit="118|125" prop="946|739|5242"/>
<sta_battlePalaceMonsterSkill id="192" pokeId="539" skill="89|157|398|370" weight="100" features="5|39|104" fruit="118|125" prop="946|739|5242"/>
<sta_battlePalaceMonsterSkill id="193" pokeId="542" skill="14|404|348|398" weight="100" features="68|34" fruit="118|125" prop="737"/>
<sta_battlePalaceMonsterSkill id="194" pokeId="542" skill="113|115|404|348" weight="100" features="68|34" fruit="118|125" prop="737"/>
<sta_battlePalaceMonsterSkill id="195" pokeId="553" skill="89|157|242|337" weight="100" features="22|83" fruit="118|125" prop="113|946"/>
<sta_battlePalaceMonsterSkill id="196" pokeId="553" skill="201|423|424|89" weight="100" features="22|83" fruit="118|125" prop="113|946"/>
<sta_battlePalaceMonsterSkill id="197" pokeId="555" skill="89|157|7|371" weight="100" features="125" fruit="118|125" prop="106|732|946"/>
<sta_battlePalaceMonsterSkill id="198" pokeId="555" skill="428|7|359|369" weight="100" features="125" fruit="118|125" prop="106|732|946"/>
<sta_battlePalaceMonsterSkill id="199" pokeId="558" skill="10479|89|404|398" weight="100" features="5|75" fruit="118|125" prop="1594|732"/>
<sta_battlePalaceMonsterSkill id="200" pokeId="558" skill="504|89|10479|398" weight="100" features="5|75" fruit="118|125" prop="1594|732"/>
<sta_battlePalaceMonsterSkill id="201" pokeId="560" skill="136|242|337|157" weight="100" features="61|22|153" fruit="118|125" prop="946|935"/>
<sta_battlePalaceMonsterSkill id="202" pokeId="560" skill="207|269|136|371" weight="100" features="61|22|153" fruit="118|125" prop="946|935"/>
<sta_battlePalaceMonsterSkill id="203" pokeId="561" skill="403|94|247|58" weight="100" features="98|147" fruit="118|125" prop="935|955"/>
<sta_battlePalaceMonsterSkill id="204" pokeId="561" skill="113|115|94|86" weight="100" features="98|147" fruit="118|125" prop="935|955"/>
<sta_battlePalaceMonsterSkill id="205" pokeId="563" skill="261|247|94|412" weight="100" features="152" fruit="118|125" prop="1594|745"/>
<sta_battlePalaceMonsterSkill id="206" pokeId="563" skill="114|92|94|247" weight="100" features="152" fruit="118|125" prop="1594|745"/>
<sta_battlePalaceMonsterSkill id="207" pokeId="565" skill="89|157|453|504" weight="100" features="5" fruit="118|125" prop="737|732"/>
<sta_battlePalaceMonsterSkill id="208" pokeId="565" skill="89|157|401|92" weight="100" features="5" fruit="118|125" prop="737|732"/>
<sta_battlePalaceMonsterSkill id="209" pokeId="569" skill="441|10479|409|371" weight="100" features="133" fruit="118|125" prop="737|732"/>
<sta_battlePalaceMonsterSkill id="210" pokeId="569" skill="188|85|202|399" weight="100" features="133" fruit="118|125" prop="737|732"/>
<sta_battlePalaceMonsterSkill id="211" pokeId="571" skill="399|53|326|447" weight="100" features="" fruit="118|125" prop="955|935|739"/>
<sta_battlePalaceMonsterSkill id="212" pokeId="571" skill="369|421|10468|340" weight="100" features="" fruit="118|125" prop="955|935|739"/>
<sta_battlePalaceMonsterSkill id="213" pokeId="573" skill="401|541|538|231" weight="100" features="92|101" fruit="118|125" prop="946|734"/>
<sta_battlePalaceMonsterSkill id="214" pokeId="573" skill="113|86|369|541" weight="100" features="92|101" fruit="118|125" prop="946|734"/>
<sta_battlePalaceMonsterSkill id="215" pokeId="576" skill="94|247|85|412" weight="100" features="23" fruit="118|125" prop="955|935"/>
<sta_battlePalaceMonsterSkill id="216" pokeId="576" skill="113|115|94|243" weight="100" features="23" fruit="118|125" prop="955|935"/>
<sta_battlePalaceMonsterSkill id="217" pokeId="579" skill="94|247|412|411" weight="100" features="98|142" fruit="118|125" prop="1594|955|745"/>
<sta_battlePalaceMonsterSkill id="218" pokeId="579" skill="113|115|94|85" weight="100" features="98|142" fruit="118|125" prop="1594|955|745"/>
<sta_battlePalaceMonsterSkill id="219" pokeId="581" skill="240|57|58|542" weight="100" features="145|51" fruit="118|125" prop="737|739"/>
<sta_battlePalaceMonsterSkill id="220" pokeId="581" skill="355|92|403|57" weight="100" features="145|51" fruit="118|125" prop="737|739"/>
<sta_battlePalaceMonsterSkill id="221" pokeId="584" skill="58|430|324|352" weight="100" features="115" fruit="118|125" prop="955|1594|734"/>
<sta_battlePalaceMonsterSkill id="222" pokeId="584" skill="258|59|113|92" weight="100" features="115" fruit="118|125" prop="955|1594|734"/>
<sta_battlePalaceMonsterSkill id="223" pokeId="589" skill="14|404|442|332" weight="100" features="68|75" fruit="118|125" prop="732|737|946"/>
<sta_battlePalaceMonsterSkill id="224" pokeId="589" skill="398|565|442|529" weight="100" features="68|75" fruit="118|125" prop="732|737|946"/>
<sta_battlePalaceMonsterSkill id="225" pokeId="591" skill="92|412|202|188" weight="100" features="27" fruit="118|125" prop="1594|939|734"/>
<sta_battlePalaceMonsterSkill id="226" pokeId="591" skill="92|275|148|202" weight="100" features="27" fruit="118|125" prop="1594|939|734"/>
<sta_battlePalaceMonsterSkill id="227" pokeId="594" skill="94|247|58|57" weight="100" features="93" fruit="118|125" prop="745|737|109"/>
<sta_battlePalaceMonsterSkill id="228" pokeId="594" skill="113|92|243|503" weight="100" features="93" fruit="118|125" prop="745|737|109"/>
<sta_battlePalaceMonsterSkill id="229" pokeId="596" skill="405|85|412|86" weight="100" features="14|127" fruit="118|125" prop="955|734|935"/>
<sta_battlePalaceMonsterSkill id="230" pokeId="596" skill="564|92|527|202" weight="100" features="14|127" fruit="118|125" prop="955|734|935"/>
<sta_battlePalaceMonsterSkill id="231" pokeId="598" skill="360|402|371|398" weight="100" features="160" fruit="118|125" prop="1594|737|745"/>
<sta_battlePalaceMonsterSkill id="232" pokeId="598" skill="153|73|92|446" weight="100" features="160" fruit="118|125" prop="1594|737|745"/>
<sta_battlePalaceMonsterSkill id="233" pokeId="601" skill="544|528|86|393" weight="100" features="29" fruit="118|125" prop="1594|732|955"/>
<sta_battlePalaceMonsterSkill id="234" pokeId="601" skill="92|207|433|201" weight="100" features="29" fruit="118|125" prop="1594|732|955"/>
<sta_battlePalaceMonsterSkill id="235" pokeId="604" skill="85|430|53|406" weight="100" features="26" fruit="118|125" prop="935|739"/>
<sta_battlePalaceMonsterSkill id="236" pokeId="604" skill="337|7|9|401" weight="100" features="26" fruit="118|125" prop="935|739"/>
<sta_battlePalaceMonsterSkill id="237" pokeId="606" skill="94|247|412|85" weight="100" features="28" fruit="118|125" prop="737|935"/>
<sta_battlePalaceMonsterSkill id="238" pokeId="606" skill="433|115|113|94" weight="100" features="28" fruit="118|125" prop="737|935"/>
<sta_battlePalaceMonsterSkill id="239" pokeId="609" skill="247|53|94|399" weight="100" features="18|49|151" fruit="118|125" prop="732|733|745|853|945"/>
<sta_battlePalaceMonsterSkill id="240" pokeId="609" skill="241|53|76|247" weight="100" features="18|49|151" fruit="118|125" prop="955|935"/>
<sta_battlePalaceMonsterSkill id="241" pokeId="612" skill="337|89|157|398" weight="100" features="79|104|127" fruit="118|125" prop="107|946"/>
<sta_battlePalaceMonsterSkill id="242" pokeId="612" skill="269|207|92|337" weight="100" features="79|104|127" fruit="118|125" prop="107|946"/>
<sta_battlePalaceMonsterSkill id="243" pokeId="614" skill="157|8|583|276" weight="100" features="81" fruit="118|125" prop="946|122"/>
<sta_battlePalaceMonsterSkill id="244" pokeId="614" skill="14|523|444|8" weight="100" features="81" fruit="118|125" prop="946|122"/>
<sta_battlePalaceMonsterSkill id="245" pokeId="615" skill="258|113|115|105" weight="100" features="26" fruit="118|125" prop="1594|112|732"/>
<sta_battlePalaceMonsterSkill id="246" pokeId="615" skill="58|430|352|105" weight="100" features="26" fruit="118|125" prop="1594|112|732"/>
<sta_battlePalaceMonsterSkill id="247" pokeId="620" skill="369|157|398|136" weight="100" features="39|144|120" fruit="118|125" prop="739|946"/>
<sta_battlePalaceMonsterSkill id="248" pokeId="620" skill="396|369|447|129" weight="100" features="39|144|120" fruit="118|125" prop="739|946"/>
<sta_battlePalaceMonsterSkill id="249" pokeId="625" skill="400|442|398|14" weight="100" features="39|46" fruit="118|125" prop="739|946|935"/>
<sta_battlePalaceMonsterSkill id="250" pokeId="625" skill="400|442|86|444" weight="100" features="39|46" fruit="118|125" prop="739|946|935"/>
<sta_battlePalaceMonsterSkill id="251" pokeId="628" skill="306|211|413|421" weight="100" features="51|125" fruit="118|125" prop="946|950"/>
<sta_battlePalaceMonsterSkill id="252" pokeId="628" skill="157|369|306|413" weight="100" features="51|125" fruit="118|125" prop="946|950"/>
<sta_battlePalaceMonsterSkill id="253" pokeId="630" skill="92|355|399|403" weight="100" features="145|142" fruit="118|125" prop="1594|745"/>
<sta_battlePalaceMonsterSkill id="254" pokeId="630" skill="399|403|247|369" weight="100" features="145|142" fruit="118|125" prop="1594|745"/>
<sta_battlePalaceMonsterSkill id="255" pokeId="631" skill="53|202|92|269" weight="100" features="18" fruit="118|125" prop="737|106"/>
<sta_battlePalaceMonsterSkill id="256" pokeId="631" skill="241|53|76|92" weight="100" features="18" fruit="118|125" prop="737|106"/>
<sta_battlePalaceMonsterSkill id="257" pokeId="632" skill="404|442|157|91" weight="100" features="68|55" fruit="118|125" prop="1594|739|946"/>
<sta_battlePalaceMonsterSkill id="258" pokeId="632" skill="404|442|422|421" weight="100" features="68|55" fruit="118|125" prop="1594|739|946"/>
<sta_battlePalaceMonsterSkill id="259" pokeId="635" skill="406|399|53|414" weight="100" features="26" fruit="118|125" prop="107|732|955|5242"/>
<sta_battlePalaceMonsterSkill id="260" pokeId="635" skill="242|422|423|424" weight="100" features="26" fruit="118|125" prop="107|732|955|5242"/>
<sta_battlePalaceMonsterSkill id="261" pokeId="10129" skill="150|33|175|340" weight="100" features="33|22" fruit="118|125" prop="946|739"/>
<sta_battlePalaceMonsterSkill id="262" pokeId="10129" skill="340|33|175|329" weight="100" features="33|22" fruit="118|125" prop="946|739"/>
<sta_battlePalaceMonsterSkill id="263" pokeId="201479" skill="85|247|399|315" weight="100" features="26" fruit="118|125" prop="955|935"/>
<sta_battlePalaceMonsterSkill id="264" pokeId="201479" skill="261|435|521|466" weight="100" features="26" fruit="118|125" prop="955|935"/>
<sta_battlePalaceMonsterSkill id="265" pokeId="202479" skill="85|247|399|56" weight="100" features="26" fruit="118|125" prop="955|935"/>
<sta_battlePalaceMonsterSkill id="266" pokeId="202479" skill="261|435|521|466" weight="100" features="26" fruit="118|125" prop="955|935"/>
<sta_battlePalaceMonsterSkill id="267" pokeId="203479" skill="85|247|399|59" weight="100" features="26" fruit="118|125" prop="955|935"/>
<sta_battlePalaceMonsterSkill id="268" pokeId="203479" skill="261|435|521|466" weight="100" features="26" fruit="118|125" prop="955|935"/>
<sta_battlePalaceMonsterSkill id="269" pokeId="204479" skill="85|247|399|403" weight="100" features="26" fruit="118|125" prop="955|935"/>
<sta_battlePalaceMonsterSkill id="270" pokeId="204479" skill="261|435|521|466" weight="100" features="26" fruit="118|125" prop="955|935"/>
<sta_battlePalaceMonsterSkill id="271" pokeId="205479" skill="85|247|399|437" weight="100" features="26" fruit="118|125" prop="955|935"/>
<sta_battlePalaceMonsterSkill id="272" pokeId="205479" skill="261|435|521|466" weight="100" features="26" fruit="118|125" prop="955|935"/>
<sta_battlePalaceMonsterSkill id="273" pokeId="3" skill="73|230|235|46" weight="100" features="65|34" fruit="118|125" prop="939|1601|1594"/>
<sta_battlePalaceMonsterSkill id="274" pokeId="3" skill="241|76|188|73" weight="100" features="65|34" fruit="118|125" prop="939|1601|1594"/>
<sta_battlePalaceMonsterSkill id="275" pokeId="3" skill="412|164|89|188" weight="100" features="65|34" fruit="118|125" prop="939|1601|1594"/>
<sta_battlePalaceMonsterSkill id="276" pokeId="3" skill="447|92|113|580" weight="100" features="65|34" fruit="118|125" prop="939|1601|1594"/>
<sta_battlePalaceMonsterSkill id="277" pokeId="6" skill="394|403|53|76" weight="100" features="66|94" fruit="118|125" prop="1602|106|745"/>
<sta_battlePalaceMonsterSkill id="278" pokeId="6" skill="315|488|126|261" weight="100" features="66|94" fruit="118|125" prop="1602|106|745"/>
<sta_battlePalaceMonsterSkill id="279" pokeId="6" skill="525|261|411|53" weight="100" features="66|94" fruit="118|125" prop="1602|106|745"/>
<sta_battlePalaceMonsterSkill id="280" pokeId="6" skill="257|164|207|355" weight="100" features="66|94" fruit="118|125" prop="1602|106|745"/>
<sta_battlePalaceMonsterSkill id="281" pokeId="9" skill="229|56|110|92" weight="100" features="67|44" fruit="118|125" prop="1603|109|1594"/>
<sta_battlePalaceMonsterSkill id="282" pokeId="9" skill="258|46|317|56" weight="100" features="67|44" fruit="118|125" prop="1603|109|1594"/>
<sta_battlePalaceMonsterSkill id="283" pokeId="9" skill="58|56|401|89" weight="100" features="67|44" fruit="118|125" prop="1603|109|1594"/>
<sta_battlePalaceMonsterSkill id="284" pokeId="9" skill="10479|104|92|89" weight="100" features="67|44" fruit="118|125" prop="1603|109|1594"/>
<sta_battlePalaceMonsterSkill id="285" pokeId="65" skill="94|347|105|115" weight="100" features="26|28|39|98|36" fruit="118|125" prop="935|110"/>
<sta_battlePalaceMonsterSkill id="286" pokeId="65" skill="94|247|447|86" weight="100" features="26|28|39|98|36" fruit="118|125" prop="935|110"/>
<sta_battlePalaceMonsterSkill id="287" pokeId="65" skill="86|104|94|164" weight="100" features="26|28|39|98|36" fruit="118|125" prop="935|110"/>
<sta_battlePalaceMonsterSkill id="288" pokeId="65" skill="605|259|94|92" weight="100" features="26|28|39|98|36" fruit="118|125" prop="935|110"/>
<sta_battlePalaceMonsterSkill id="289" pokeId="80" skill="174|281|94|156" weight="100" features="144|12" fruit="118|125" prop="109|745|5242"/>
<sta_battlePalaceMonsterSkill id="290" pokeId="80" skill="58|94|89|126" weight="100" features="144|12" fruit="118|125" prop="109|745|5242"/>
<sta_battlePalaceMonsterSkill id="291" pokeId="80" skill="156|219|57|94" weight="100" features="144|12" fruit="118|125" prop="109|745|5242"/>
<sta_battlePalaceMonsterSkill id="292" pokeId="80" skill="240|247|94|503" weight="100" features="144|12" fruit="118|125" prop="109|745|5242"/>
<sta_battlePalaceMonsterSkill id="293" pokeId="94" skill="194|92|188|247" weight="100" features="26|130" fruit="118|125" prop="935|737"/>
<sta_battlePalaceMonsterSkill id="294" pokeId="94" skill="85|94|247|261" weight="100" features="26|130" fruit="118|125" prop="935|737"/>
<sta_battlePalaceMonsterSkill id="295" pokeId="94" skill="269|605|399|247" weight="100" features="26|130" fruit="118|125" prop="935|737"/>
<sta_battlePalaceMonsterSkill id="296" pokeId="94" skill="412|92|109|247" weight="100" features="26|130" fruit="118|125" prop="935|737"/>
<sta_battlePalaceMonsterSkill id="297" pokeId="115" skill="612|146|179|89" weight="100" features="48|39" fruit="118|125" prop="108|5245|745"/>
<sta_battlePalaceMonsterSkill id="298" pokeId="115" skill="126|156|89|280" weight="100" features="48|39" fruit="118|125" prop="108|5245|745"/>
<sta_battlePalaceMonsterSkill id="299" pokeId="115" skill="201|89|58|63" weight="100" features="48|39" fruit="118|125" prop="108|5245|745"/>
<sta_battlePalaceMonsterSkill id="300" pokeId="115" skill="164|421|276|509" weight="100" features="48|39" fruit="118|125" prop="108|5245|745"/>
<sta_battlePalaceMonsterSkill id="301" pokeId="130" skill="423|127|242|184" weight="100" features="22" fruit="118|125" prop="946|745"/>
<sta_battlePalaceMonsterSkill id="302" pokeId="130" skill="349|240|46|127" weight="100" features="22" fruit="118|125" prop="946|745"/>
<sta_battlePalaceMonsterSkill id="303" pokeId="130" skill="89|444|525|127" weight="100" features="22" fruit="118|125" prop="946|745"/>
<sta_battlePalaceMonsterSkill id="304" pokeId="130" skill="371|200|349|127" weight="100" features="22" fruit="118|125" prop="946|745"/>
<sta_battlePalaceMonsterSkill id="305" pokeId="142" skill="10468|444|442|355" weight="100" features="46|127|69" fruit="118|125" prop="5242|5241|946"/>
<sta_battlePalaceMonsterSkill id="306" pokeId="142" skill="332|355|269|92" weight="100" features="46|127|69" fruit="118|125" prop="5242|5241|946"/>
<sta_battlePalaceMonsterSkill id="307" pokeId="142" skill="46|337|157|332" weight="100" features="46|127|69" fruit="118|125" prop="5242|5241|946"/>
<sta_battlePalaceMonsterSkill id="308" pokeId="142" skill="89|104|444|10479" weight="100" features="46|127|69" fruit="118|125" prop="5242|5241|946"/>
<sta_battlePalaceMonsterSkill id="309" pokeId="145" skill="365|435|86|113" weight="100" features="31|46" fruit="118|125" prop="935|114"/>
<sta_battlePalaceMonsterSkill id="310" pokeId="145" skill="355|92|85|65" weight="100" features="31|46" fruit="118|125" prop="935|114"/>
<sta_battlePalaceMonsterSkill id="311" pokeId="145" skill="97|113|85|211" weight="100" features="31|46" fruit="118|125" prop="935|114"/>
<sta_battlePalaceMonsterSkill id="312" pokeId="145" skill="86|521|85|19" weight="100" features="31|46" fruit="118|125" prop="935|114"/>
<sta_battlePalaceMonsterSkill id="313" pokeId="149" skill="7|8|9|97" weight="100" features="136|61" fruit="118|125" prop="5574|745"/>
<sta_battlePalaceMonsterSkill id="314" pokeId="149" skill="200|97|17|89" weight="100" features="136|61" fruit="118|125" prop="5574|745"/>
<sta_battlePalaceMonsterSkill id="315" pokeId="149" skill="211|200|355|126" weight="100" features="136|61" fruit="118|125" prop="5574|745"/>
<sta_battlePalaceMonsterSkill id="316" pokeId="149" skill="127|525|157|200" weight="100" features="136|61" fruit="118|125" prop="5574|745"/>
<sta_battlePalaceMonsterSkill id="317" pokeId="248" skill="242|157|89|424" weight="100" features="45|127" fruit="118|125" prop="3571|745|5242|5241"/>
<sta_battlePalaceMonsterSkill id="318" pokeId="248" skill="444|423|89|242" weight="100" features="45|127" fruit="118|125" prop="3571|745|5242|5241"/>
<sta_battlePalaceMonsterSkill id="319" pokeId="248" skill="242|280|86|259" weight="100" features="45|127" fruit="118|125" prop="3571|745|5242|5241"/>
<sta_battlePalaceMonsterSkill id="320" pokeId="248" skill="525|242|92|156" weight="100" features="45|127" fruit="118|125" prop="3571|745|5242|5241"/>
<sta_battlePalaceMonsterSkill id="321" pokeId="254" skill="412|332|157|89" weight="100" features="22|65" fruit="118|125" prop="5223|737"/>
<sta_battlePalaceMonsterSkill id="322" pokeId="254" skill="164|447|157|404" weight="100" features="22|65" fruit="118|125" prop="5223|737"/>
<sta_battlePalaceMonsterSkill id="323" pokeId="254" skill="235|388|520|67" weight="100" features="22|65" fruit="118|125" prop="5223|737"/>
<sta_battlePalaceMonsterSkill id="324" pokeId="254" skill="116|406|348|89" weight="100" features="22|65" fruit="118|125" prop="5223|737"/>
<sta_battlePalaceMonsterSkill id="325" pokeId="257" skill="299|98|280|14" weight="100" features="66" fruit="118|125" prop="5225|737|732"/>
<sta_battlePalaceMonsterSkill id="326" pokeId="257" skill="299|317|226|14" weight="100" features="66" fruit="118|125" prop="5225|737|732"/>
<sta_battlePalaceMonsterSkill id="327" pokeId="257" skill="421|261|299|444" weight="100" features="66" fruit="118|125" prop="5225|737|732"/>
<sta_battlePalaceMonsterSkill id="328" pokeId="257" skill="299|488|116|327" weight="100" features="66" fruit="118|125" prop="5225|737|732"/>
<sta_battlePalaceMonsterSkill id="329" pokeId="260" skill="89|57|8|156" weight="100" features="67" fruit="118|125" prop="5224|946|745"/>
<sta_battlePalaceMonsterSkill id="330" pokeId="260" skill="89|157|127|92" weight="100" features="67" fruit="118|125" prop="5224|946|745"/>
<sta_battlePalaceMonsterSkill id="331" pokeId="260" skill="46|156|127|89" weight="100" features="67" fruit="118|125" prop="5224|946|745"/>
<sta_battlePalaceMonsterSkill id="332" pokeId="260" skill="8|157|127|250" weight="100" features="67" fruit="118|125" prop="5224|946|745"/>
<sta_battlePalaceMonsterSkill id="333" pokeId="306" skill="92|7|232|276" weight="100" features="5|111" fruit="118|125" prop="737|1594|5242|5241"/>
<sta_battlePalaceMonsterSkill id="334" pokeId="306" skill="8|442|7|89" weight="100" features="5|111" fruit="118|125" prop="737|1594|5242|5241"/>
<sta_battlePalaceMonsterSkill id="335" pokeId="306" skill="92|156|419|484" weight="100" features="5|111" fruit="118|125" prop="737|1594|5242|5241"/>
<sta_battlePalaceMonsterSkill id="336" pokeId="306" skill="231|46|457|174" weight="100" features="5|111" fruit="118|125" prop="737|1594|5242|5241"/>
<sta_battlePalaceMonsterSkill id="337" pokeId="334" skill="365|219|349|406" weight="100" features="13" fruit="118|125" prop="745"/>
<sta_battlePalaceMonsterSkill id="338" pokeId="334" skill="585|413|355|92" weight="100" features="13" fruit="118|125" prop="745"/>
<sta_battlePalaceMonsterSkill id="339" pokeId="334" skill="337|126|585|89" weight="100" features="13" fruit="118|125" prop="745"/>
<sta_battlePalaceMonsterSkill id="340" pokeId="334" skill="244|407|114|211" weight="100" features="13" fruit="118|125" prop="745"/>
<sta_battlePalaceMonsterSkill id="341" pokeId="359" skill="104|14|364|400" weight="100" features="46|154" fruit="118|125" prop="739"/>
<sta_battlePalaceMonsterSkill id="342" pokeId="359" skill="427|400|98|163" weight="100" features="46|154" fruit="118|125" prop="739"/>
<sta_battlePalaceMonsterSkill id="343" pokeId="359" skill="92|400|53|269" weight="100" features="46|154" fruit="118|125" prop="739"/>
<sta_battlePalaceMonsterSkill id="344" pokeId="359" skill="14|86|400|444" weight="100" features="46|154" fruit="118|125" prop="739"/>
<sta_battlePalaceMonsterSkill id="345" pokeId="376" skill="309|94|334|92" weight="100" features="5|80|75|29" fruit="118|125" prop="732|946"/>
<sta_battlePalaceMonsterSkill id="346" pokeId="376" skill="312|317|156|89" weight="100" features="5|80|75|29" fruit="118|125" prop="732|946"/>
<sta_battlePalaceMonsterSkill id="347" pokeId="376" skill="309|115|113|188" weight="100" features="5|80|75|29" fruit="118|125" prop="732|946"/>
<sta_battlePalaceMonsterSkill id="348" pokeId="376" skill="309|156|94|214" weight="100" features="5|80|75|29" fruit="118|125" prop="732|946"/>
<sta_battlePalaceMonsterSkill id="349" pokeId="448" skill="396|247|156|214" weight="100" features="39|80|154" fruit="118|125" prop="5572|739|935"/>
<sta_battlePalaceMonsterSkill id="350" pokeId="448" skill="417|396|430|164" weight="100" features="39|80|154" fruit="118|125" prop="5572|739|935"/>
<sta_battlePalaceMonsterSkill id="351" pokeId="448" skill="370|396|157|442" weight="100" features="39|80|154" fruit="118|125" prop="5572|739|935"/>
<sta_battlePalaceMonsterSkill id="352" pokeId="448" skill="370|444|8|245" weight="100" features="39|80|154" fruit="118|125" prop="5572|739|935"/>
<sta_battlePalaceMonsterSkill id="353" pokeId="475" skill="370|332|14|10473" weight="100" features="80|154" fruit="118|125" prop="946|935|739"/>
<sta_battlePalaceMonsterSkill id="354" pokeId="475" skill="182|364|104|219" weight="100" features="80|154" fruit="118|125" prop="946|935|739"/>
<sta_battlePalaceMonsterSkill id="355" pokeId="475" skill="115|317|89|113" weight="100" features="80|154" fruit="118|125" prop="946|935|739"/>
<sta_battlePalaceMonsterSkill id="356" pokeId="475" skill="261|14|444|370" weight="100" features="80|154" fruit="118|125" prop="946|935|739"/>
<sta_battlePalaceMonsterSkill id="357" pokeId="15" skill="42|283|280|398" weight="100" features="14|101" fruit="118|125" prop="115|105|739"/>
<sta_battlePalaceMonsterSkill id="358" pokeId="15" skill="14|398|369|529" weight="100" features="14|101" fruit="118|125" prop="115|105|739"/>
<sta_battlePalaceMonsterSkill id="359" pokeId="310" skill="53|85|324|63" weight="100" features="211" fruit="118|125" prop="116|935"/>
<sta_battlePalaceMonsterSkill id="360" pokeId="310" skill="422|423|424|242" weight="100" features="211" fruit="118|125" prop="116|935"/>
<sta_battlePalaceMonsterSkill id="361" pokeId="282" skill="115|86|577|94" weight="100" features="28|36" fruit="118|125" prop="110|935|955"/>
<sta_battlePalaceMonsterSkill id="362" pokeId="282" skill="109|86|451|94" weight="100" features="28|36" fruit="118|125" prop="110|935|955"/>
<sta_battlePalaceMonsterSkill id="363" pokeId="282" skill="94|585|85|247" weight="100" features="28|36" fruit="118|125" prop="110|935|955"/>
<sta_battlePalaceMonsterSkill id="364" pokeId="297" skill="89|280|10479|418" weight="100" features="125|62" fruit="118|125" prop="745|5242|5241|946"/>
<sta_battlePalaceMonsterSkill id="365" pokeId="297" skill="523|157|280|398" weight="100" features="125|62" fruit="118|125" prop="745|5242|5241|946"/>
<sta_battlePalaceMonsterSkill id="366" pokeId="637" skill="10483|53|405|542" weight="100" features="49" fruit="118|125" prop="950|106|955"/>
<sta_battlePalaceMonsterSkill id="367" pokeId="637" skill="241|53|76|405" weight="100" features="49" fruit="118|125" prop="950|106|955"/>
<sta_battlePalaceMonsterSkill id="368" pokeId="162" skill="7|8|9|489" weight="100" features="" fruit="118|125" prop="108|737"/>
<sta_battlePalaceMonsterSkill id="369" pokeId="206" skill="34|529|355|407" weight="100" features="" fruit="118|125" prop="737|745"/>
<sta_battlePalaceMonsterSkill id="370" pokeId="24" skill="305|422|423|424" weight="100" features="" fruit="118|125" prop="115|935"/>
<sta_battlePalaceMonsterSkill id="371" pokeId="20" skill="242|172|158|14" weight="100" features="" fruit="118|125" prop="739|108"/>
<sta_battlePalaceMonsterSkill id="372" pokeId="47" skill="440|147|404|153" weight="100" features="" fruit="118|125" prop="737"/>
<sta_battlePalaceMonsterSkill id="373" pokeId="49" skill="10483|405|188|94" weight="100" features="" fruit="118|125" prop="105|737"/>
<sta_battlePalaceMonsterSkill id="374" pokeId="53" skill="492|400|163|583" weight="100" features="" fruit="118|125" prop="739|108"/>
<sta_battlePalaceMonsterSkill id="375" pokeId="119" skill="529|127|224|398" weight="100" features="" fruit="118|125" prop="946|5245|745"/>
<sta_battlePalaceMonsterSkill id="376" pokeId="164" skill="403|94|355|304" weight="100" features="110" fruit="118|125" prop="737|955"/>
<sta_battlePalaceMonsterSkill id="377" pokeId="168" skill="425|14|398|450" weight="100" features="" fruit="118|125" prop="737"/>
<sta_battlePalaceMonsterSkill id="378" pokeId="166" skill="14|409|8|9" weight="100" features="" fruit="118|125" prop="737"/>
<sta_battlePalaceMonsterSkill id="379" pokeId="185" skill="68|444|452|492" weight="100" features="" fruit="118|125" prop="737"/>
<sta_battlePalaceMonsterSkill id="380" pokeId="192" skill="73|202|80|414" weight="100" features="" fruit="118|125" prop="737"/>
<sta_battlePalaceMonsterSkill id="381" pokeId="195" skill="8|127|157|89" weight="100" features="11|109" fruit="118|125" prop="737|732"/>
<sta_battlePalaceMonsterSkill id="382" pokeId="203" skill="247|85|94|417" weight="100" features="48|157" fruit="118|125" prop="737|110|935"/>
<sta_battlePalaceMonsterSkill id="383" pokeId="211" skill="191|390|194|153" weight="100" features="" fruit="118|125" prop="745|1594"/>
<sta_battlePalaceMonsterSkill id="384" pokeId="219" skill="446|246|414|53" weight="100" features="" fruit="118|125" prop="737"/>
<sta_battlePalaceMonsterSkill id="385" pokeId="222" skill="243|446|113|115" weight="100" features="" fruit="118|125" prop="737"/>
<sta_battlePalaceMonsterSkill id="386" pokeId="106" skill="490|157|89|299" weight="100" features="" fruit="118|125" prop="946|739|5242"/>
<sta_battlePalaceMonsterSkill id="387" pokeId="107" skill="418|7|8|9" weight="100" features="" fruit="118|125" prop="946|739|5242"/>
<sta_battlePalaceMonsterSkill id="388" pokeId="237" skill="157|89|418|370" weight="100" features="" fruit="118|125" prop="946|739|5242"/>
<sta_battlePalaceMonsterSkill id="389" pokeId="262" skill="242|422|423|424" weight="100" features="" fruit="118|125" prop="737"/>
<sta_battlePalaceMonsterSkill id="390" pokeId="279" skill="355|57|542|240" weight="100" features="" fruit="118|125" prop="737"/>
<sta_battlePalaceMonsterSkill id="391" pokeId="284" skill="412|403|405|10483" weight="100" features="" fruit="118|125" prop="737"/>
<sta_battlePalaceMonsterSkill id="392" pokeId="400" skill="14|158|242|127" weight="100" features="" fruit="118|125" prop="737"/>
<sta_battlePalaceMonsterSkill id="393" pokeId="441" skill="257|314|304|417" weight="100" features="" fruit="118|125" prop="737"/>
<sta_battlePalaceMonsterSkill id="394" pokeId="457" skill="250|318|324|392" weight="100" features="" fruit="118|125" prop="737"/>
<sta_battlePalaceMonsterSkill id="395" pokeId="528" skill="403|94|355|412" weight="100" features="" fruit="118|125" prop="737"/>
<sta_battlePalaceMonsterSkill id="396" pokeId="184" skill="583|127|523|340" weight="100" features="" fruit="118|125" prop="1594"/>
<sta_battlePalaceMonsterSkill id="397" pokeId="210" skill="242|422|423|583" weight="100" features="" fruit="118|125" prop="745|946"/>
</root>